MANIFEST.in
README.md
pyproject.toml
setup.cfg
setup.py
asyncio_simple_mq.egg-info/PKG-INFO
asyncio_simple_mq.egg-info/SOURCES.txt
asyncio_simple_mq.egg-info/dependency_links.txt
asyncio_simple_mq.egg-info/requires.txt
asyncio_simple_mq.egg-info/top_level.txt
simplemq/__init__.py
simplemq/bind.py
simplemq/connection.py
simplemq/hints.py
simplemq/member.py
simplemq/mixins.py
simplemq/adapters/__init__.py
simplemq/adapters/socket.py
simplemq/follower/__init__.py
simplemq/follower/follower.py
simplemq/logger_conf/__init__.py
simplemq/logger_conf/logger_setup.py
simplemq/message_package/__init__.py
simplemq/message_package/convert_message_to_bytes.py
simplemq/message_package/create_server_message.py
simplemq/message_package/deserializer.py
simplemq/message_package/id_generator.py
simplemq/message_package/message_classes.py
simplemq/message_package/message_factory.py
simplemq/publisher/__init__.py
simplemq/publisher/publisher.py
simplemq/server/__init__.py
simplemq/server/data.py
simplemq/server/dispatcher_by_sender_type.py
simplemq/server/exceptions.py
simplemq/server/request_type_handlers.py
simplemq/server/server.py
simplemq/server/stream_writer_wrapper.py