Metadata-Version: 2.1
Name: asyncio-simple-mq
Version: 1.0.0
Summary: asyncio-simple-mq
Home-page: https://github.com/Rwwwrl/SimpleMQ
Author: Alexey Sosov
Author-email: lesh.solowiew@yandex.ru
License: BSD-3-Clause
Classifier: Environment :: Web Environment
Classifier: Intended Audience :: Developers
Classifier: License :: OSI Approved :: BSD License
Classifier: Operating System :: OS Independent
Classifier: Programming Language :: Python :: 3.7
Classifier: Programming Language :: Python :: 3.8
Classifier: Programming Language :: Python :: 3.9
Classifier: Programming Language :: Python :: 3.10
Requires-Python: >=3.7
